extract_answer_key/__init__.py
extract_answer_key/__main__.py
extract_answer_key/functions.py
extract_answer_key/main.py
extract_answer_key-0.1.23.dist-info/METADATA
extract_answer_key-0.1.23.dist-info/WHEEL
extract_answer_key-0.1.23.dist-info/entry_points.txt
extract_answer_key-0.1.23.dist-info/RECORD
