Metadata-Version: 2.1
Name: extract-answer-key
Version: 0.1.23
Summary: Added support for integer answer keys with random numbering  
Author: vaibhavblayer
Author-email: vaibhavblayer@gmail.com
Requires-Python: >=3.11,<4.0
Classifier: Programming Language :: Python :: 3
Classifier: Programming Language :: Python :: 3.11
Requires-Dist: click (>=8.1.7,<9.0.0)
